tkintermd/__init__.py
tkintermd/__main__.py
tkintermd/constants.py
tkintermd/frame.py
tkintermd/log.py
tkintermd-0.0.6.dist-info/LICENSE
tkintermd-0.0.6.dist-info/LICENSE.txt
tkintermd-0.0.6.dist-info/METADATA
tkintermd-0.0.6.dist-info/WHEEL
tkintermd-0.0.6.dist-info/entry_points.txt
tkintermd-0.0.6.dist-info/top_level.txt
tkintermd-0.0.6.dist-info/RECORD
