Metadata-Version: 2.1
Name: tkintermd
Version: 0.0.6
Summary: A Python based Markdown editor with HTML preview
Home-page: https://github.com/hreikin/tkintermd
Author: hreikin
Author-email: hreikin@gmail.com
License: MIT
Platform: UNKNOWN
Classifier: License :: OSI Approved :: MIT License
Classifier: Programming Language :: Python :: 3
Classifier: Programming Language :: Python :: 3.7
Classifier: Programming Language :: Python :: 3.8
Classifier: Programming Language :: Python :: 3.9
Classifier: Programming Language :: Python :: 3.10
License-File: LICENSE
License-File: LICENSE.txt
Requires-Dist: markdown
Requires-Dist: pygments
Requires-Dist: pymdown-extensions
Requires-Dist: tkinterweb
